{
	"id": "bsKHtJEmPo3PlXl",
	"json": "{\"id\":\"bsKHtJEmPo3PlXl\",\"url\":\"https://www.worldofbooks.com/en-gb/pages/international-booker-prize\",\"loadedUrl\":\"https://www.worldofbooks.com/en-gb/pages/international-booker-prize\",\"uniqueKey\":\"https://www.worldofbooks.com/en-gb/pages/international-booker-prize\",\"method\":\"GET\",\"noRetry\":false,\"retryCount\":0,\"errorMessages\":[],\"headers\":{},\"userData\":{\"__crawlee\":{\"crawlDepth\":1,\"enqueueStrategy\":\"same-domain\",\"state\":4}},\"handledAt\":\"2026-01-15T12:53:20.204Z\"}",
	"method": "GET",
	"orderNo": null,
	"retryCount": 0,
	"uniqueKey": "https://www.worldofbooks.com/en-gb/pages/international-booker-prize",
	"url": "https://www.worldofbooks.com/en-gb/pages/international-booker-prize"
}