{
  "requestsFinished": 0,
  "requestsFailed": 0,
  "requestsRetries": 0,
  "requestsFailedPerMinute": 0,
  "requestsFinishedPerMinute": 0,
  "requestMinDurationMillis": null,
  "requestMaxDurationMillis": 0,
  "requestTotalFailedDurationMillis": 0,
  "requestTotalFinishedDurationMillis": 0,
  "crawlerStartedAt": "2026-01-10T21:28:36.247Z",
  "crawlerFinishedAt": "2026-01-10T21:28:39.838Z",
  "statsPersistedAt": "2026-01-10T21:28:39.838Z",
  "crawlerRuntimeMillis": 4201,
  "crawlerLastStartTimestamp": 1768080515637,
  "requestRetryHistogram": [],
  "statsId": 1,
  "requestAvgFailedDurationMillis": null,
  "requestAvgFinishedDurationMillis": null,
  "requestTotalDurationMillis": 0,
  "requestsTotal": 0,
  "requestsWithStatusCode": {},
  "errors": {},
  "retryErrors": {}
}